{
  "appId": "com.algoux.kessoku-broadcaster",
  "productName": "Kessoku the Broadcaster",
  "files": ["dist/electron/**", "dist/ui/**"],
  "extraResources": [
    "dist/electron/preload.cts",
    {
      "from": "resources/ffmpeg",
      "to": "ffmpeg",
      "filter": ["**/*"]
    },
    {
      "from": "resources",
      "to": "resources",
      "filter": ["*.png", "*.jpg", "*.jpeg", "*.ico"]
    }
  ],
  "generateUpdatesFilesForAllChannels": false,
  "mac": {
    "target": "dmg",
    "icon": "resources/icon/icon.icns"
  },
  "linux": {
    "target": "AppImage",
    "category": "Utility"
  },
  "win": {
    "target": ["portable", "msi"]
  }
}
